{
  "$schema": "https://json.schemastore.org/jsdoc",
  "source": {
    "include": ["src"],
    "includePattern": "\\.(jsx|js|ts|tsx)$",
    "excludePattern": "(node_modules|test|__tests__|__mocks__|dist|build)"
  },
  "sourceType": "module",
  "plugins": ["plugins/markdown"],
  "opts": {
    "destination": "./docs",
    "recurse": true,
    "readme": "./README.md",
    "template": "templates/default",
    "encoding": "utf8",
    "verbose": true
  },
  "tags": {
    "allowUnknownTags": true,
    "dictionaries": ["jsdoc", "closure"]
  },
  "templates": {
    "cleverLinks": true,
    "monospaceLinks": true,
    "default": {
      "outputSourceFiles": true,
      "includeDate": false,
      "useLongnameInNav": true
    }
  },
  "markdown": {
    "parser": "gfm",
    "hardwrap": false,
    "idInHeadings": true
  }
}
